{
  "name": "CWF-430 Audio Script Optimizer Canonical",
  "description": "Optimizes script for audio delivery with timing marks and pacing.",
  "nodes": [
    {
      "parameters": {},
      "id": "trigger",
      "name": "Trigger",
      "type": "n8n-nodes-base.executeWorkflowTrigger",
      "typeVersion": 1,
      "position": [
        200,
        300
      ]
    },
    {
      "parameters": {
        "jsCode": "const audio = {instance_id: 'AUDIO-' + Date.now(), artifact_family: 'audio_optimized_script_packet', schema_version: '1.0.0', producer_workflow: 'CWF-430', dossier_ref: $json.dossier_id, created_at: new Date().toISOString(), status: 'CREATED', payload: {audio_optimization_complete: true, voiceover_style: 'conversational', estimated_duration_seconds: 300, pacing_markers: ['pause_point_1', 'emphasis_section', 'pause_point_2'], music_cues: [{point: 'intro', duration_seconds: 5}, {point: 'transition', duration_seconds: 2}, {point: 'outro', duration_seconds: 8}], sound_design_notes: 'minimal_enhancement_applied', optimization_confidence: 0.92}};\nreturn [{ json: { ...$json, cwf430_result: { status: 'COMPLETED', audio_optimized_script_packet: audio } } }];"
      },
      "id": "builder",
      "name": "Builder",
      "type": "n8n-nodes-base.code",
      "typeVersion": 2,
      "position": [
        420,
        300
      ]
    },
    {
      "parameters": {
        "jsCode": "try {\n  const SkillLoader = require('../../../engine/skill_loader/skill_loader.js');\n  const loader = new SkillLoader();\n\n  if (!loader.skills_registry || Object.keys(loader.skills_registry).length === 0) {\n    const initResult = await loader.initialize();\n    if (initResult.status !== 'initialized') {\n      throw new Error('Failed to initialize SkillLoader');\n    }\n  }\n\n  const workflowId = 'CWF-430';\n  const defaultSkillMap = {\"CWF-310\":\"M-001\",\"CWF-320\":\"M-001\",\"CWF-330\":\"M-001\",\"CWF-340\":\"M-001\",\"CWF-410\":\"M-001\",\"CWF-420\":\"M-001\",\"CWF-430\":\"M-001\",\"CWF-440\":\"M-001\",\"CWF-510\":\"M-001\",\"CWF-520\":\"M-001\",\"CWF-530\":\"M-001\"};\n  const skillId = $json.skill_id || defaultSkillMap[workflowId] || 'M-001';\n  const dossierId = $json.dossier_context?.dossier_id || $json.dossier_id || 'DOSSIER-UNSPECIFIED';\n\n  const contextPacket = {\n    dossier_id: dossierId,\n    workflow_id: workflowId,\n    ...(typeof $json.user_context === 'object' ? $json.user_context : {}),\n    ...(typeof $json.route_context === 'object' ? $json.route_context : {})\n  };\n\n  const dossierState = typeof $json.dossier === 'object' ? $json.dossier : {};\n  const result = await loader.executeSkill(skillId, contextPacket, dossierState);\n\n  return [{\n    json: {\n      ...$json,\n      phase8_runtime_probe: {\n        workflow_id: workflowId,\n        skill_id: skillId,\n        status: result.status,\n        had_error: result.status !== 'SUCCESS',\n        error_message: result.status === 'SUCCESS' ? '' : String(result.error || ''),\n        timestamp: new Date().toISOString()\n      },\n      runtime_packet: result.status === 'SUCCESS' ? (result.output || null) : null,\n      skill_execution_result: result.status === 'SUCCESS' ? result : null,\n      runtime: {\n        had_error: result.status !== 'SUCCESS',\n        error_message: result.status === 'SUCCESS' ? '' : String(result.error || '')\n      }\n    }\n  }];\n} catch (error) {\n  const message = String(error && error.message ? error.message : error);\n  return [{\n    json: {\n      ...$json,\n      phase8_runtime_probe: {\n        workflow_id: 'CWF-430',\n        skill_id: null,\n        status: 'ERROR',\n        had_error: true,\n        error_message: message,\n        timestamp: new Date().toISOString()\n      },\n      runtime_packet: null,\n      skill_execution_result: null,\n      runtime: { had_error: true, error_message: message }\n    }\n  }];\n}"
      },
      "id": "cwf_430_skill_runtime_probe_node",
      "name": "Skill Runtime Probe Node",
      "type": "n8n-nodes-base.code",
      "typeVersion": 2,
      "position": [
        420,
        300
      ]
    }
  ],
  "connections": {
    "Trigger": {
      "main": [
        [
          {
            "node": "Skill Runtime Probe Node",
            "type": "main",
            "index": 0
          }
        ]
      ]
    },
    "Builder": {
      "main": [
        []
      ]
    },
    "Skill Runtime Probe Node": {
      "main": [
        [
          {
            "node": "Builder",
            "type": "main",
            "index": 0
          }
        ]
      ]
    }
  },
  "meta": {
    "workflow_id": "CWF-430",
    "phase": "phase4",
    "vein": "media_vein",
    "purpose": "Video composition (deferred).",
    "implementation_depth": "phase_deferred_stub",
    "owner_director": "narada",
    "next_workflow": "CWF-440",
    "canonical_file": "n8n/workflows/CWF-430.json",
    "wf900_error_route": "WF-900"
  },
  "active": true
}